{
  "source": {
    "status": "live_api",
    "platform": "klaviyo",
    "message": "Klaviyo email/SMS attribution fetched directly from Klaviyo APIs."
  },
  "window": {
    "dateFrom": "2026-04-01",
    "dateTo": "2026-04-20"
  },
  "account": {
    "id": "U9rq9t",
    "organizationName": "Diamond Plus s.r.o.",
    "senderName": "Království tianDe",
    "senderEmail": "info@kralovstvi-tiande.cz",
    "websiteUrl": "http://www.kralovstvi-tiande.cz",
    "timezone": "Europe/Prague",
    "preferredCurrency": "CZK",
    "publicApiKey": "U9rq9t"
  },
  "metrics": {
    "placed_order": {
      "id": "Y7vfdc",
      "name": "Placed Order"
    },
    "received_email": {
      "id": "TEf87t",
      "name": "Received Email"
    },
    "opened_email": {
      "id": "VsEZBW",
      "name": "Opened Email"
    },
    "clicked_email": {
      "id": "Xf6T8r",
      "name": "Clicked Email"
    },
    "received_sms": {
      "id": "SWAP9s",
      "name": "Received SMS"
    },
    "clicked_sms": {
      "id": "UK2GDV",
      "name": "Clicked SMS"
    }
  },
  "currentMonth": {
    "dateFrom": "2026-04-01",
    "dateTo": "2026-04-20",
    "emailAttributedRevenueCzk": 3189716.05,
    "smsAttributedRevenueCzk": 0.0,
    "emailAttributedOrders": 2096.0,
    "smsAttributedOrders": 0.0,
    "emailRecipients": 500272.0,
    "smsRecipients": 0.0,
    "emailClicks": 24293.0,
    "smsClicks": 0.0,
    "totalAttributedRevenueCzk": 3189716.05,
    "totalAttributedOrders": 2096.0,
    "totalRecipients": 500272.0,
    "totalClicks": 24293.0,
    "clickRate": 0.0486
  },
  "dailySummary": [
    {
      "date": "2026-04-01",
      "emailAttributedRevenueCzk": 122529.3,
      "smsAttributedRevenueCzk": 0.0,
      "totalAttributedRevenueCzk": 122529.3,
      "emailAttributedOrders": 106.0,
      "smsAttributedOrders": 0.0,
      "totalAttributedOrders": 106.0,
      "emailRecipients": 52140.0,
      "smsRecipients": 0.0,
      "totalRecipients": 52140.0,
      "emailClicks": 2077.0,
      "smsClicks": 0.0,
      "totalClicks": 2077.0,
      "clickRate": 0.0398
    },
    {
      "date": "2026-04-02",
      "emailAttributedRevenueCzk": 156687.95,
      "smsAttributedRevenueCzk": 0.0,
      "totalAttributedRevenueCzk": 156687.95,
      "emailAttributedOrders": 93.0,
      "smsAttributedOrders": 0.0,
      "totalAttributedOrders": 93.0,
      "emailRecipients": 29106.0,
      "smsRecipients": 0.0,
      "totalRecipients": 29106.0,
      "emailClicks": 1084.0,
      "smsClicks": 0.0,
      "totalClicks": 1084.0,
      "clickRate": 0.0372
    },
    {
      "date": "2026-04-03",
      "emailAttributedRevenueCzk": 76304.3,
      "smsAttributedRevenueCzk": 0.0,
      "totalAttributedRevenueCzk": 76304.3,
      "emailAttributedOrders": 54.0,
      "smsAttributedOrders": 0.0,
      "totalAttributedOrders": 54.0,
      "emailRecipients": 26140.0,
      "smsRecipients": 0.0,
      "totalRecipients": 26140.0,
      "emailClicks": 877.0,
      "smsClicks": 0.0,
      "totalClicks": 877.0,
      "clickRate": 0.0336
    },
    {
      "date": "2026-04-04",
      "emailAttributedRevenueCzk": 85824.55,
      "smsAttributedRevenueCzk": 0.0,
      "totalAttributedRevenueCzk": 85824.55,
      "emailAttributedOrders": 63.0,
      "smsAttributedOrders": 0.0,
      "totalAttributedOrders": 63.0,
      "emailRecipients": 23342.0,
      "smsRecipients": 0.0,
      "totalRecipients": 23342.0,
      "emailClicks": 556.0,
      "smsClicks": 0.0,
      "totalClicks": 556.0,
      "clickRate": 0.0238
    },
    {
      "date": "2026-04-05",
      "emailAttributedRevenueCzk": 101801.7,
      "smsAttributedRevenueCzk": 0.0,
      "totalAttributedRevenueCzk": 101801.7,
      "emailAttributedOrders": 76.0,
      "smsAttributedOrders": 0.0,
      "totalAttributedOrders": 76.0,
      "emailRecipients": 21259.0,
      "smsRecipients": 0.0,
      "totalRecipients": 21259.0,
      "emailClicks": 665.0,
      "smsClicks": 0.0,
      "totalClicks": 665.0,
      "clickRate": 0.0313
    },
    {
      "date": "2026-04-06",
      "emailAttributedRevenueCzk": 228482.55,
      "smsAttributedRevenueCzk": 0.0,
      "totalAttributedRevenueCzk": 228482.55,
      "emailAttributedOrders": 158.0,
      "smsAttributedOrders": 0.0,
      "totalAttributedOrders": 158.0,
      "emailRecipients": 46221.0,
      "smsRecipients": 0.0,
      "totalRecipients": 46221.0,
      "emailClicks": 1178.0,
      "smsClicks": 0.0,
      "totalClicks": 1178.0,
      "clickRate": 0.0255
    },
    {
      "date": "2026-04-07",
      "emailAttributedRevenueCzk": 253221.65,
      "smsAttributedRevenueCzk": 0.0,
      "totalAttributedRevenueCzk": 253221.65,
      "emailAttributedOrders": 185.0,
      "smsAttributedOrders": 0.0,
      "totalAttributedOrders": 185.0,
      "emailRecipients": 30800.0,
      "smsRecipients": 0.0,
      "totalRecipients": 30800.0,
      "emailClicks": 2208.0,
      "smsClicks": 0.0,
      "totalClicks": 2208.0,
      "clickRate": 0.0717
    },
    {
      "date": "2026-04-08",
      "emailAttributedRevenueCzk": 100646.8,
      "smsAttributedRevenueCzk": 0.0,
      "totalAttributedRevenueCzk": 100646.8,
      "emailAttributedOrders": 60.0,
      "smsAttributedOrders": 0.0,
      "totalAttributedOrders": 60.0,
      "emailRecipients": 28492.0,
      "smsRecipients": 0.0,
      "totalRecipients": 28492.0,
      "emailClicks": 2203.0,
      "smsClicks": 0.0,
      "totalClicks": 2203.0,
      "clickRate": 0.0773
    },
    {
      "date": "2026-04-09",
      "emailAttributedRevenueCzk": 198392.05,
      "smsAttributedRevenueCzk": 0.0,
      "totalAttributedRevenueCzk": 198392.05,
      "emailAttributedOrders": 116.0,
      "smsAttributedOrders": 0.0,
      "totalAttributedOrders": 116.0,
      "emailRecipients": 28833.0,
      "smsRecipients": 0.0,
      "totalRecipients": 28833.0,
      "emailClicks": 1603.0,
      "smsClicks": 0.0,
      "totalClicks": 1603.0,
      "clickRate": 0.0556
    },
    {
      "date": "2026-04-10",
      "emailAttributedRevenueCzk": 130806.0,
      "smsAttributedRevenueCzk": 0.0,
      "totalAttributedRevenueCzk": 130806.0,
      "emailAttributedOrders": 74.0,
      "smsAttributedOrders": 0.0,
      "totalAttributedOrders": 74.0,
      "emailRecipients": 576.0,
      "smsRecipients": 0.0,
      "totalRecipients": 576.0,
      "emailClicks": 666.0,
      "smsClicks": 0.0,
      "totalClicks": 666.0,
      "clickRate": 1.1562
    },
    {
      "date": "2026-04-11",
      "emailAttributedRevenueCzk": 59110.05,
      "smsAttributedRevenueCzk": 0.0,
      "totalAttributedRevenueCzk": 59110.05,
      "emailAttributedOrders": 41.0,
      "smsAttributedOrders": 0.0,
      "totalAttributedOrders": 41.0,
      "emailRecipients": 501.0,
      "smsRecipients": 0.0,
      "totalRecipients": 501.0,
      "emailClicks": 279.0,
      "smsClicks": 0.0,
      "totalClicks": 279.0,
      "clickRate": 0.5569
    },
    {
      "date": "2026-04-12",
      "emailAttributedRevenueCzk": 109867.5,
      "smsAttributedRevenueCzk": 0.0,
      "totalAttributedRevenueCzk": 109867.5,
      "emailAttributedOrders": 72.0,
      "smsAttributedOrders": 0.0,
      "totalAttributedOrders": 72.0,
      "emailRecipients": 21116.0,
      "smsRecipients": 0.0,
      "totalRecipients": 21116.0,
      "emailClicks": 563.0,
      "smsClicks": 0.0,
      "totalClicks": 563.0,
      "clickRate": 0.0267
    },
    {
      "date": "2026-04-13",
      "emailAttributedRevenueCzk": 292374.0,
      "smsAttributedRevenueCzk": 0.0,
      "totalAttributedRevenueCzk": 292374.0,
      "emailAttributedOrders": 165.0,
      "smsAttributedOrders": 0.0,
      "totalAttributedOrders": 165.0,
      "emailRecipients": 24967.0,
      "smsRecipients": 0.0,
      "totalRecipients": 24967.0,
      "emailClicks": 1600.0,
      "smsClicks": 0.0,
      "totalClicks": 1600.0,
      "clickRate": 0.0641
    },
    {
      "date": "2026-04-14",
      "emailAttributedRevenueCzk": 513080.25,
      "smsAttributedRevenueCzk": 0.0,
      "totalAttributedRevenueCzk": 513080.25,
      "emailAttributedOrders": 306.0,
      "smsAttributedOrders": 0.0,
      "totalAttributedOrders": 306.0,
      "emailRecipients": 51173.0,
      "smsRecipients": 0.0,
      "totalRecipients": 51173.0,
      "emailClicks": 3157.0,
      "smsClicks": 0.0,
      "totalClicks": 3157.0,
      "clickRate": 0.0617
    },
    {
      "date": "2026-04-15",
      "emailAttributedRevenueCzk": 174127.1,
      "smsAttributedRevenueCzk": 0.0,
      "totalAttributedRevenueCzk": 174127.1,
      "emailAttributedOrders": 128.0,
      "smsAttributedOrders": 0.0,
      "totalAttributedOrders": 128.0,
      "emailRecipients": 30628.0,
      "smsRecipients": 0.0,
      "totalRecipients": 30628.0,
      "emailClicks": 2363.0,
      "smsClicks": 0.0,
      "totalClicks": 2363.0,
      "clickRate": 0.0772
    },
    {
      "date": "2026-04-16",
      "emailAttributedRevenueCzk": 142194.85,
      "smsAttributedRevenueCzk": 0.0,
      "totalAttributedRevenueCzk": 142194.85,
      "emailAttributedOrders": 98.0,
      "smsAttributedOrders": 0.0,
      "totalAttributedOrders": 98.0,
      "emailRecipients": 3509.0,
      "smsRecipients": 0.0,
      "totalRecipients": 3509.0,
      "emailClicks": 675.0,
      "smsClicks": 0.0,
      "totalClicks": 675.0,
      "clickRate": 0.1924
    },
    {
      "date": "2026-04-17",
      "emailAttributedRevenueCzk": 80829.4,
      "smsAttributedRevenueCzk": 0.0,
      "totalAttributedRevenueCzk": 80829.4,
      "emailAttributedOrders": 60.0,
      "smsAttributedOrders": 0.0,
      "totalAttributedOrders": 60.0,
      "emailRecipients": 26606.0,
      "smsRecipients": 0.0,
      "totalRecipients": 26606.0,
      "emailClicks": 481.0,
      "smsClicks": 0.0,
      "totalClicks": 481.0,
      "clickRate": 0.0181
    },
    {
      "date": "2026-04-18",
      "emailAttributedRevenueCzk": 55959.25,
      "smsAttributedRevenueCzk": 0.0,
      "totalAttributedRevenueCzk": 55959.25,
      "emailAttributedOrders": 41.0,
      "smsAttributedOrders": 0.0,
      "totalAttributedOrders": 41.0,
      "emailRecipients": 379.0,
      "smsRecipients": 0.0,
      "totalRecipients": 379.0,
      "emailClicks": 313.0,
      "smsClicks": 0.0,
      "totalClicks": 313.0,
      "clickRate": 0.8259
    },
    {
      "date": "2026-04-19",
      "emailAttributedRevenueCzk": 159305.5,
      "smsAttributedRevenueCzk": 0.0,
      "totalAttributedRevenueCzk": 159305.5,
      "emailAttributedOrders": 96.0,
      "smsAttributedOrders": 0.0,
      "totalAttributedOrders": 96.0,
      "emailRecipients": 26257.0,
      "smsRecipients": 0.0,
      "totalRecipients": 26257.0,
      "emailClicks": 548.0,
      "smsClicks": 0.0,
      "totalClicks": 548.0,
      "clickRate": 0.0209
    },
    {
      "date": "2026-04-20",
      "emailAttributedRevenueCzk": 148098.25,
      "smsAttributedRevenueCzk": 0.0,
      "totalAttributedRevenueCzk": 148098.25,
      "emailAttributedOrders": 103.0,
      "smsAttributedOrders": 0.0,
      "totalAttributedOrders": 103.0,
      "emailRecipients": 28193.0,
      "smsRecipients": 0.0,
      "totalRecipients": 28193.0,
      "emailClicks": 1188.0,
      "smsClicks": 0.0,
      "totalClicks": 1188.0,
      "clickRate": 0.0421
    },
    {
      "date": "2026-04-21",
      "emailAttributedRevenueCzk": 73.05,
      "smsAttributedRevenueCzk": 0.0,
      "totalAttributedRevenueCzk": 73.05,
      "emailAttributedOrders": 1.0,
      "smsAttributedOrders": 0.0,
      "totalAttributedOrders": 1.0,
      "emailRecipients": 34.0,
      "smsRecipients": 0.0,
      "totalRecipients": 34.0,
      "emailClicks": 9.0,
      "smsClicks": 0.0,
      "totalClicks": 9.0,
      "clickRate": 0.2647
    }
  ],
  "flowsCurrentMonth": [
    {
      "flowId": "SXtWxm",
      "flowName": "Opuštěný košík - Standard",
      "status": "live",
      "triggerType": "Metric",
      "channel": "email",
      "attributedOrders": 112.0,
      "attributedRevenueCzk": 155823.7,
      "messageCount": 4,
      "messageNames": [
        "Abandoned Cart: Email 1",
        "Abandoned Cart: Email 2",
        "Abandoned Cart: Email 3",
        "Abandoned Cart: Email 4"
      ],
      "recipients": 8111.0,
      "opens": 1776.0,
      "clicks": 225.0,
      "openRate": 0.219,
      "clickRate": 0.0277,
      "conversionRate": 0.0138
    },
    {
      "flowId": "VTgVba",
      "flowName": "Happy Birthday - Standard",
      "status": "live",
      "triggerType": "Date Based",
      "channel": "email",
      "attributedOrders": 33.0,
      "attributedRevenueCzk": 55620.75,
      "messageCount": 1,
      "messageNames": [
        "Dárek k narozeninám"
      ],
      "recipients": 846.0,
      "opens": 731.0,
      "clicks": 111.0,
      "openRate": 0.8641,
      "clickRate": 0.1312,
      "conversionRate": 0.039
    },
    {
      "flowId": "TFpngU",
      "flowName": "Kvíz Detox",
      "status": "live",
      "triggerType": "Metric",
      "channel": "email",
      "attributedOrders": 20.0,
      "attributedRevenueCzk": 45912.0,
      "messageCount": 4,
      "messageNames": [
        "Email #1 - prevence",
        "Email #1 - střední zátěž",
        "vysoká zátěž",
        "Email #4"
      ],
      "recipients": 384.0,
      "opens": 281.0,
      "clicks": 132.0,
      "openRate": 0.7318,
      "clickRate": 0.3438,
      "conversionRate": 0.0521
    },
    {
      "flowId": "R5fKfn",
      "flowName": "Přihláška - potvrzení , kurs tělo jako kompas",
      "status": "live",
      "triggerType": "Metric",
      "channel": "email",
      "attributedOrders": 33.0,
      "attributedRevenueCzk": 45659.45,
      "messageCount": 1,
      "messageNames": [
        "potvrzení přihlášy"
      ],
      "recipients": 1170.0,
      "opens": 1744.0,
      "clicks": 1283.0,
      "openRate": 1.4906,
      "clickRate": 1.0966,
      "conversionRate": 0.0282
    },
    {
      "flowId": "VqgfET",
      "flowName": "Bonusové body - připsání",
      "status": "live",
      "triggerType": "Metric",
      "channel": "email",
      "attributedOrders": 35.0,
      "attributedRevenueCzk": 38352.85,
      "messageCount": 1,
      "messageNames": [
        "Email #1"
      ],
      "recipients": 1606.0,
      "opens": 691.0,
      "clicks": 82.0,
      "openRate": 0.4303,
      "clickRate": 0.0511,
      "conversionRate": 0.0218
    },
    {
      "flowId": "SxBynF",
      "flowName": "Webinář - potvrzení registrace",
      "status": "live",
      "triggerType": "Metric",
      "channel": "email",
      "attributedOrders": 14.0,
      "attributedRevenueCzk": 30472.0,
      "messageCount": 1,
      "messageNames": [
        "Potvrzení registrace na webinář"
      ],
      "recipients": 415.0,
      "opens": 536.0,
      "clicks": 118.0,
      "openRate": 1.2916,
      "clickRate": 0.2843,
      "conversionRate": 0.0337
    },
    {
      "flowId": "UTrftt",
      "flowName": "Přihláška Sebeláska - potvrzení",
      "status": "live",
      "triggerType": "Metric",
      "channel": "email",
      "attributedOrders": 2.0,
      "attributedRevenueCzk": 2930.95,
      "messageCount": 1,
      "messageNames": [
        "Email #1"
      ],
      "recipients": 143.0,
      "opens": 112.0,
      "clicks": 9.0,
      "openRate": 0.7832,
      "clickRate": 0.0629,
      "conversionRate": 0.014
    },
    {
      "flowId": "XXhjck",
      "flowName": "Registrae Kurz hubnutí 2",
      "status": "live",
      "triggerType": "Metric",
      "channel": "email",
      "attributedOrders": 2.0,
      "attributedRevenueCzk": 2694.0,
      "messageCount": 1,
      "messageNames": [
        "Email #1"
      ],
      "recipients": 40.0,
      "opens": 207.0,
      "clicks": 237.0,
      "openRate": 5.175,
      "clickRate": 5.925,
      "conversionRate": 0.05
    },
    {
      "flowId": "SLW4ei",
      "flowName": "tianDe - upozornění na dárky",
      "status": "live",
      "triggerType": "Metric",
      "channel": "email",
      "attributedOrders": 4.0,
      "attributedRevenueCzk": 1960.8,
      "messageCount": 1,
      "messageNames": [
        "Info o připravených dárcích"
      ],
      "recipients": 95.0,
      "opens": 53.0,
      "clicks": 4.0,
      "openRate": 0.5579,
      "clickRate": 0.0421,
      "conversionRate": 0.0421
    },
    {
      "flowId": "WMS3b5",
      "flowName": "welcome - brožury - bez bolesti",
      "status": "live",
      "triggerType": "Added to List",
      "channel": "email",
      "attributedOrders": 1.0,
      "attributedRevenueCzk": 1040.0,
      "messageCount": 9,
      "messageNames": [
        "Email #1",
        "Email #2",
        "Email #3",
        "Email #4",
        "Email #5"
      ],
      "recipients": 605.0,
      "opens": 169.0,
      "clicks": 45.0,
      "openRate": 0.2793,
      "clickRate": 0.0744,
      "conversionRate": 0.0017
    }
  ],
  "topFlowsCurrentMonth": [
    {
      "flowId": "SXtWxm",
      "flowName": "Opuštěný košík - Standard",
      "status": "live",
      "triggerType": "Metric",
      "channel": "email",
      "attributedOrders": 112.0,
      "attributedRevenueCzk": 155823.7,
      "messageCount": 4,
      "messageNames": [
        "Abandoned Cart: Email 1",
        "Abandoned Cart: Email 2",
        "Abandoned Cart: Email 3",
        "Abandoned Cart: Email 4"
      ],
      "recipients": 8111.0,
      "opens": 1776.0,
      "clicks": 225.0,
      "openRate": 0.219,
      "clickRate": 0.0277,
      "conversionRate": 0.0138
    },
    {
      "flowId": "VTgVba",
      "flowName": "Happy Birthday - Standard",
      "status": "live",
      "triggerType": "Date Based",
      "channel": "email",
      "attributedOrders": 33.0,
      "attributedRevenueCzk": 55620.75,
      "messageCount": 1,
      "messageNames": [
        "Dárek k narozeninám"
      ],
      "recipients": 846.0,
      "opens": 731.0,
      "clicks": 111.0,
      "openRate": 0.8641,
      "clickRate": 0.1312,
      "conversionRate": 0.039
    },
    {
      "flowId": "TFpngU",
      "flowName": "Kvíz Detox",
      "status": "live",
      "triggerType": "Metric",
      "channel": "email",
      "attributedOrders": 20.0,
      "attributedRevenueCzk": 45912.0,
      "messageCount": 4,
      "messageNames": [
        "Email #1 - prevence",
        "Email #1 - střední zátěž",
        "vysoká zátěž",
        "Email #4"
      ],
      "recipients": 384.0,
      "opens": 281.0,
      "clicks": 132.0,
      "openRate": 0.7318,
      "clickRate": 0.3438,
      "conversionRate": 0.0521
    },
    {
      "flowId": "R5fKfn",
      "flowName": "Přihláška - potvrzení , kurs tělo jako kompas",
      "status": "live",
      "triggerType": "Metric",
      "channel": "email",
      "attributedOrders": 33.0,
      "attributedRevenueCzk": 45659.45,
      "messageCount": 1,
      "messageNames": [
        "potvrzení přihlášy"
      ],
      "recipients": 1170.0,
      "opens": 1744.0,
      "clicks": 1283.0,
      "openRate": 1.4906,
      "clickRate": 1.0966,
      "conversionRate": 0.0282
    },
    {
      "flowId": "VqgfET",
      "flowName": "Bonusové body - připsání",
      "status": "live",
      "triggerType": "Metric",
      "channel": "email",
      "attributedOrders": 35.0,
      "attributedRevenueCzk": 38352.85,
      "messageCount": 1,
      "messageNames": [
        "Email #1"
      ],
      "recipients": 1606.0,
      "opens": 691.0,
      "clicks": 82.0,
      "openRate": 0.4303,
      "clickRate": 0.0511,
      "conversionRate": 0.0218
    },
    {
      "flowId": "SxBynF",
      "flowName": "Webinář - potvrzení registrace",
      "status": "live",
      "triggerType": "Metric",
      "channel": "email",
      "attributedOrders": 14.0,
      "attributedRevenueCzk": 30472.0,
      "messageCount": 1,
      "messageNames": [
        "Potvrzení registrace na webinář"
      ],
      "recipients": 415.0,
      "opens": 536.0,
      "clicks": 118.0,
      "openRate": 1.2916,
      "clickRate": 0.2843,
      "conversionRate": 0.0337
    },
    {
      "flowId": "UTrftt",
      "flowName": "Přihláška Sebeláska - potvrzení",
      "status": "live",
      "triggerType": "Metric",
      "channel": "email",
      "attributedOrders": 2.0,
      "attributedRevenueCzk": 2930.95,
      "messageCount": 1,
      "messageNames": [
        "Email #1"
      ],
      "recipients": 143.0,
      "opens": 112.0,
      "clicks": 9.0,
      "openRate": 0.7832,
      "clickRate": 0.0629,
      "conversionRate": 0.014
    },
    {
      "flowId": "XXhjck",
      "flowName": "Registrae Kurz hubnutí 2",
      "status": "live",
      "triggerType": "Metric",
      "channel": "email",
      "attributedOrders": 2.0,
      "attributedRevenueCzk": 2694.0,
      "messageCount": 1,
      "messageNames": [
        "Email #1"
      ],
      "recipients": 40.0,
      "opens": 207.0,
      "clicks": 237.0,
      "openRate": 5.175,
      "clickRate": 5.925,
      "conversionRate": 0.05
    },
    {
      "flowId": "SLW4ei",
      "flowName": "tianDe - upozornění na dárky",
      "status": "live",
      "triggerType": "Metric",
      "channel": "email",
      "attributedOrders": 4.0,
      "attributedRevenueCzk": 1960.8,
      "messageCount": 1,
      "messageNames": [
        "Info o připravených dárcích"
      ],
      "recipients": 95.0,
      "opens": 53.0,
      "clicks": 4.0,
      "openRate": 0.5579,
      "clickRate": 0.0421,
      "conversionRate": 0.0421
    },
    {
      "flowId": "WMS3b5",
      "flowName": "welcome - brožury - bez bolesti",
      "status": "live",
      "triggerType": "Added to List",
      "channel": "email",
      "attributedOrders": 1.0,
      "attributedRevenueCzk": 1040.0,
      "messageCount": 9,
      "messageNames": [
        "Email #1",
        "Email #2",
        "Email #3",
        "Email #4",
        "Email #5"
      ],
      "recipients": 605.0,
      "opens": 169.0,
      "clicks": 45.0,
      "openRate": 0.2793,
      "clickRate": 0.0744,
      "conversionRate": 0.0017
    }
  ],
  "recentCampaigns": [
    {
      "id": "01KPDCK4MCFHMBG77V3SEY0JAG",
      "name": "CZ - Tělo jako kompas - 3. lekce - pozvánka",
      "channel": "email",
      "status": "Sent",
      "createdAt": "2026-04-17T09:33:14.767573+00:00",
      "updatedAt": "2026-04-20T15:01:26.779036+00:00",
      "scheduledAt": "2026-04-20T08:48:27.207250+00:00",
      "sendDatetime": "2026-04-20T15:00:00+00:00",
      "recipients": 1651.0,
      "opens": 458.0,
      "clicks": 199.0,
      "attributedOrders": 3.0,
      "attributedRevenueCzk": 4300.0,
      "openRate": 0.2774,
      "clickRate": 0.1205,
      "conversionRate": 0.0018
    },
    {
      "id": "01KPDF0GD0GGNA9FW26BBFZSTQ",
      "name": "CZ -  Měčín - ženské zdraví - už zítra",
      "channel": "email",
      "status": "Sent",
      "createdAt": "2026-04-17T10:15:29.956439+00:00",
      "updatedAt": "2026-04-20T12:00:51.544148+00:00",
      "scheduledAt": "2026-04-20T08:32:22.338109+00:00",
      "sendDatetime": "2026-04-20T12:00:00+00:00",
      "recipients": 727.0,
      "opens": 80.0,
      "clicks": 0.0,
      "attributedOrders": 1.0,
      "attributedRevenueCzk": 790.0,
      "openRate": 0.11,
      "clickRate": 0.0,
      "conversionRate": 0.0014
    },
    {
      "id": "01KPNAMETY006Y102ZA0TRBDPK",
      "name": "CZ - Slevové zemětřesení",
      "channel": "email",
      "status": "Draft",
      "createdAt": "2026-04-20T11:32:56.290169+00:00",
      "updatedAt": "2026-04-20T11:32:56.290190+00:00",
      "scheduledAt": null,
      "sendDatetime": "2026-04-20T09:15:00+00:00",
      "recipients": 0.0,
      "opens": 0.0,
      "clicks": 0.0,
      "attributedOrders": 0.0,
      "attributedRevenueCzk": 0.0,
      "openRate": null,
      "clickRate": null,
      "conversionRate": null
    },
    {
      "id": "01KPN7PYTTP0C737H6Y9HFEZ93",
      "name": "CZ - Novinka - ženšenová řada",
      "channel": "email",
      "status": "Draft",
      "createdAt": "2026-04-20T10:41:52.477680+00:00",
      "updatedAt": "2026-04-20T10:41:52.477699+00:00",
      "scheduledAt": null,
      "sendDatetime": "2026-04-20T09:15:00+00:00",
      "recipients": 0.0,
      "opens": 0.0,
      "clicks": 0.0,
      "attributedOrders": 0.0,
      "attributedRevenueCzk": 0.0,
      "openRate": null,
      "clickRate": null,
      "conversionRate": null
    }
  ],
  "previousMonth": {
    "dateFrom": "2026-03-01",
    "dateTo": "2026-03-31",
    "emailAttributedRevenueCzk": 5174886.85,
    "smsAttributedRevenueCzk": 0.0,
    "emailAttributedOrders": 3529.0,
    "smsAttributedOrders": 0.0,
    "emailRecipients": 1124419.0,
    "smsRecipients": 0.0,
    "emailClicks": 49063.0,
    "smsClicks": 0.0,
    "totalAttributedRevenueCzk": 5174886.85,
    "totalAttributedOrders": 3529.0,
    "totalRecipients": 1124419.0,
    "totalClicks": 49063.0,
    "clickRate": 0.0436
  },
  "dailySummaryPreviousMonth": [
    {
      "date": "2026-03-01",
      "emailAttributedRevenueCzk": 214089.55,
      "smsAttributedRevenueCzk": 0.0,
      "totalAttributedRevenueCzk": 214089.55,
      "emailAttributedOrders": 157.0,
      "smsAttributedOrders": 0.0,
      "totalAttributedOrders": 157.0,
      "emailRecipients": 45894.0,
      "smsRecipients": 0.0,
      "totalRecipients": 45894.0,
      "emailClicks": 1017.0,
      "smsClicks": 0.0,
      "totalClicks": 1017.0,
      "clickRate": 0.0222
    },
    {
      "date": "2026-03-02",
      "emailAttributedRevenueCzk": 176164.55,
      "smsAttributedRevenueCzk": 0.0,
      "totalAttributedRevenueCzk": 176164.55,
      "emailAttributedOrders": 128.0,
      "smsAttributedOrders": 0.0,
      "totalAttributedOrders": 128.0,
      "emailRecipients": 25306.0,
      "smsRecipients": 0.0,
      "totalRecipients": 25306.0,
      "emailClicks": 2289.0,
      "smsClicks": 0.0,
      "totalClicks": 2289.0,
      "clickRate": 0.0905
    },
    {
      "date": "2026-03-03",
      "emailAttributedRevenueCzk": 174885.1,
      "smsAttributedRevenueCzk": 0.0,
      "totalAttributedRevenueCzk": 174885.1,
      "emailAttributedOrders": 140.0,
      "smsAttributedOrders": 0.0,
      "totalAttributedOrders": 140.0,
      "emailRecipients": 45700.0,
      "smsRecipients": 0.0,
      "totalRecipients": 45700.0,
      "emailClicks": 1438.0,
      "smsClicks": 0.0,
      "totalClicks": 1438.0,
      "clickRate": 0.0315
    },
    {
      "date": "2026-03-04",
      "emailAttributedRevenueCzk": 166409.65,
      "smsAttributedRevenueCzk": 0.0,
      "totalAttributedRevenueCzk": 166409.65,
      "emailAttributedOrders": 136.0,
      "smsAttributedOrders": 0.0,
      "totalAttributedOrders": 136.0,
      "emailRecipients": 6013.0,
      "smsRecipients": 0.0,
      "totalRecipients": 6013.0,
      "emailClicks": 3015.0,
      "smsClicks": 0.0,
      "totalClicks": 3015.0,
      "clickRate": 0.5014
    },
    {
      "date": "2026-03-05",
      "emailAttributedRevenueCzk": 139994.6,
      "smsAttributedRevenueCzk": 0.0,
      "totalAttributedRevenueCzk": 139994.6,
      "emailAttributedOrders": 100.0,
      "smsAttributedOrders": 0.0,
      "totalAttributedOrders": 100.0,
      "emailRecipients": 26567.0,
      "smsRecipients": 0.0,
      "totalRecipients": 26567.0,
      "emailClicks": 1524.0,
      "smsClicks": 0.0,
      "totalClicks": 1524.0,
      "clickRate": 0.0574
    },
    {
      "date": "2026-03-06",
      "emailAttributedRevenueCzk": 198958.75,
      "smsAttributedRevenueCzk": 0.0,
      "totalAttributedRevenueCzk": 198958.75,
      "emailAttributedOrders": 172.0,
      "smsAttributedOrders": 0.0,
      "totalAttributedOrders": 172.0,
      "emailRecipients": 28276.0,
      "smsRecipients": 0.0,
      "totalRecipients": 28276.0,
      "emailClicks": 1216.0,
      "smsClicks": 0.0,
      "totalClicks": 1216.0,
      "clickRate": 0.043
    },
    {
      "date": "2026-03-07",
      "emailAttributedRevenueCzk": 310019.1,
      "smsAttributedRevenueCzk": 0.0,
      "totalAttributedRevenueCzk": 310019.1,
      "emailAttributedOrders": 256.0,
      "smsAttributedOrders": 0.0,
      "totalAttributedOrders": 256.0,
      "emailRecipients": 45342.0,
      "smsRecipients": 0.0,
      "totalRecipients": 45342.0,
      "emailClicks": 1044.0,
      "smsClicks": 0.0,
      "totalClicks": 1044.0,
      "clickRate": 0.023
    },
    {
      "date": "2026-03-08",
      "emailAttributedRevenueCzk": 95899.7,
      "smsAttributedRevenueCzk": 0.0,
      "totalAttributedRevenueCzk": 95899.7,
      "emailAttributedOrders": 70.0,
      "smsAttributedOrders": 0.0,
      "totalAttributedOrders": 70.0,
      "emailRecipients": 45350.0,
      "smsRecipients": 0.0,
      "totalRecipients": 45350.0,
      "emailClicks": 931.0,
      "smsClicks": 0.0,
      "totalClicks": 931.0,
      "clickRate": 0.0205
    },
    {
      "date": "2026-03-09",
      "emailAttributedRevenueCzk": 149709.3,
      "smsAttributedRevenueCzk": 0.0,
      "totalAttributedRevenueCzk": 149709.3,
      "emailAttributedOrders": 91.0,
      "smsAttributedOrders": 0.0,
      "totalAttributedOrders": 91.0,
      "emailRecipients": 47537.0,
      "smsRecipients": 0.0,
      "totalRecipients": 47537.0,
      "emailClicks": 3024.0,
      "smsClicks": 0.0,
      "totalClicks": 3024.0,
      "clickRate": 0.0636
    },
    {
      "date": "2026-03-10",
      "emailAttributedRevenueCzk": 159024.9,
      "smsAttributedRevenueCzk": 0.0,
      "totalAttributedRevenueCzk": 159024.9,
      "emailAttributedOrders": 92.0,
      "smsAttributedOrders": 0.0,
      "totalAttributedOrders": 92.0,
      "emailRecipients": 30138.0,
      "smsRecipients": 0.0,
      "totalRecipients": 30138.0,
      "emailClicks": 1617.0,
      "smsClicks": 0.0,
      "totalClicks": 1617.0,
      "clickRate": 0.0537
    },
    {
      "date": "2026-03-11",
      "emailAttributedRevenueCzk": 261428.45,
      "smsAttributedRevenueCzk": 0.0,
      "totalAttributedRevenueCzk": 261428.45,
      "emailAttributedOrders": 117.0,
      "smsAttributedOrders": 0.0,
      "totalAttributedOrders": 117.0,
      "emailRecipients": 5071.0,
      "smsRecipients": 0.0,
      "totalRecipients": 5071.0,
      "emailClicks": 2420.0,
      "smsClicks": 0.0,
      "totalClicks": 2420.0,
      "clickRate": 0.4772
    },
    {
      "date": "2026-03-12",
      "emailAttributedRevenueCzk": 342167.45,
      "smsAttributedRevenueCzk": 0.0,
      "totalAttributedRevenueCzk": 342167.45,
      "emailAttributedOrders": 191.0,
      "smsAttributedOrders": 0.0,
      "totalAttributedOrders": 191.0,
      "emailRecipients": 49864.0,
      "smsRecipients": 0.0,
      "totalRecipients": 49864.0,
      "emailClicks": 1697.0,
      "smsClicks": 0.0,
      "totalClicks": 1697.0,
      "clickRate": 0.034
    },
    {
      "date": "2026-03-13",
      "emailAttributedRevenueCzk": 140652.6,
      "smsAttributedRevenueCzk": 0.0,
      "totalAttributedRevenueCzk": 140652.6,
      "emailAttributedOrders": 92.0,
      "smsAttributedOrders": 0.0,
      "totalAttributedOrders": 92.0,
      "emailRecipients": 45369.0,
      "smsRecipients": 0.0,
      "totalRecipients": 45369.0,
      "emailClicks": 892.0,
      "smsClicks": 0.0,
      "totalClicks": 892.0,
      "clickRate": 0.0197
    },
    {
      "date": "2026-03-14",
      "emailAttributedRevenueCzk": 58177.2,
      "smsAttributedRevenueCzk": 0.0,
      "totalAttributedRevenueCzk": 58177.2,
      "emailAttributedOrders": 44.0,
      "smsAttributedOrders": 0.0,
      "totalAttributedOrders": 44.0,
      "emailRecipients": 23885.0,
      "smsRecipients": 0.0,
      "totalRecipients": 23885.0,
      "emailClicks": 646.0,
      "smsClicks": 0.0,
      "totalClicks": 646.0,
      "clickRate": 0.027
    },
    {
      "date": "2026-03-15",
      "emailAttributedRevenueCzk": 133584.95,
      "smsAttributedRevenueCzk": 0.0,
      "totalAttributedRevenueCzk": 133584.95,
      "emailAttributedOrders": 96.0,
      "smsAttributedOrders": 0.0,
      "totalAttributedOrders": 96.0,
      "emailRecipients": 48998.0,
      "smsRecipients": 0.0,
      "totalRecipients": 48998.0,
      "emailClicks": 1168.0,
      "smsClicks": 0.0,
      "totalClicks": 1168.0,
      "clickRate": 0.0238
    },
    {
      "date": "2026-03-16",
      "emailAttributedRevenueCzk": 144048.15,
      "smsAttributedRevenueCzk": 0.0,
      "totalAttributedRevenueCzk": 144048.15,
      "emailAttributedOrders": 108.0,
      "smsAttributedOrders": 0.0,
      "totalAttributedOrders": 108.0,
      "emailRecipients": 24271.0,
      "smsRecipients": 0.0,
      "totalRecipients": 24271.0,
      "emailClicks": 1388.0,
      "smsClicks": 0.0,
      "totalClicks": 1388.0,
      "clickRate": 0.0572
    },
    {
      "date": "2026-03-17",
      "emailAttributedRevenueCzk": 119981.1,
      "smsAttributedRevenueCzk": 0.0,
      "totalAttributedRevenueCzk": 119981.1,
      "emailAttributedOrders": 102.0,
      "smsAttributedOrders": 0.0,
      "totalAttributedOrders": 102.0,
      "emailRecipients": 24493.0,
      "smsRecipients": 0.0,
      "totalRecipients": 24493.0,
      "emailClicks": 1105.0,
      "smsClicks": 0.0,
      "totalClicks": 1105.0,
      "clickRate": 0.0451
    },
    {
      "date": "2026-03-18",
      "emailAttributedRevenueCzk": 203139.1,
      "smsAttributedRevenueCzk": 0.0,
      "totalAttributedRevenueCzk": 203139.1,
      "emailAttributedOrders": 129.0,
      "smsAttributedOrders": 0.0,
      "totalAttributedOrders": 129.0,
      "emailRecipients": 73290.0,
      "smsRecipients": 0.0,
      "totalRecipients": 73290.0,
      "emailClicks": 3095.0,
      "smsClicks": 0.0,
      "totalClicks": 3095.0,
      "clickRate": 0.0422
    },
    {
      "date": "2026-03-19",
      "emailAttributedRevenueCzk": 161880.1,
      "smsAttributedRevenueCzk": 0.0,
      "totalAttributedRevenueCzk": 161880.1,
      "emailAttributedOrders": 96.0,
      "smsAttributedOrders": 0.0,
      "totalAttributedOrders": 96.0,
      "emailRecipients": 24574.0,
      "smsRecipients": 0.0,
      "totalRecipients": 24574.0,
      "emailClicks": 1254.0,
      "smsClicks": 0.0,
      "totalClicks": 1254.0,
      "clickRate": 0.051
    },
    {
      "date": "2026-03-20",
      "emailAttributedRevenueCzk": 116669.65,
      "smsAttributedRevenueCzk": 0.0,
      "totalAttributedRevenueCzk": 116669.65,
      "emailAttributedOrders": 74.0,
      "smsAttributedOrders": 0.0,
      "totalAttributedOrders": 74.0,
      "emailRecipients": 21684.0,
      "smsRecipients": 0.0,
      "totalRecipients": 21684.0,
      "emailClicks": 848.0,
      "smsClicks": 0.0,
      "totalClicks": 848.0,
      "clickRate": 0.0391
    },
    {
      "date": "2026-03-21",
      "emailAttributedRevenueCzk": 120896.8,
      "smsAttributedRevenueCzk": 0.0,
      "totalAttributedRevenueCzk": 120896.8,
      "emailAttributedOrders": 72.0,
      "smsAttributedOrders": 0.0,
      "totalAttributedOrders": 72.0,
      "emailRecipients": 21565.0,
      "smsRecipients": 0.0,
      "totalRecipients": 21565.0,
      "emailClicks": 768.0,
      "smsClicks": 0.0,
      "totalClicks": 768.0,
      "clickRate": 0.0356
    },
    {
      "date": "2026-03-22",
      "emailAttributedRevenueCzk": 273717.55,
      "smsAttributedRevenueCzk": 0.0,
      "totalAttributedRevenueCzk": 273717.55,
      "emailAttributedOrders": 181.0,
      "smsAttributedOrders": 0.0,
      "totalAttributedOrders": 181.0,
      "emailRecipients": 46802.0,
      "smsRecipients": 0.0,
      "totalRecipients": 46802.0,
      "emailClicks": 1266.0,
      "smsClicks": 0.0,
      "totalClicks": 1266.0,
      "clickRate": 0.0271
    },
    {
      "date": "2026-03-23",
      "emailAttributedRevenueCzk": 107884.55,
      "smsAttributedRevenueCzk": 0.0,
      "totalAttributedRevenueCzk": 107884.55,
      "emailAttributedOrders": 83.0,
      "smsAttributedOrders": 0.0,
      "totalAttributedOrders": 83.0,
      "emailRecipients": 24065.0,
      "smsRecipients": 0.0,
      "totalRecipients": 24065.0,
      "emailClicks": 1697.0,
      "smsClicks": 0.0,
      "totalClicks": 1697.0,
      "clickRate": 0.0705
    },
    {
      "date": "2026-03-24",
      "emailAttributedRevenueCzk": 104007.05,
      "smsAttributedRevenueCzk": 0.0,
      "totalAttributedRevenueCzk": 104007.05,
      "emailAttributedOrders": 77.0,
      "smsAttributedOrders": 0.0,
      "totalAttributedOrders": 77.0,
      "emailRecipients": 52451.0,
      "smsRecipients": 0.0,
      "totalRecipients": 52451.0,
      "emailClicks": 2010.0,
      "smsClicks": 0.0,
      "totalClicks": 2010.0,
      "clickRate": 0.0383
    },
    {
      "date": "2026-03-25",
      "emailAttributedRevenueCzk": 159751.85,
      "smsAttributedRevenueCzk": 0.0,
      "totalAttributedRevenueCzk": 159751.85,
      "emailAttributedOrders": 109.0,
      "smsAttributedOrders": 0.0,
      "totalAttributedOrders": 109.0,
      "emailRecipients": 24640.0,
      "smsRecipients": 0.0,
      "totalRecipients": 24640.0,
      "emailClicks": 2223.0,
      "smsClicks": 0.0,
      "totalClicks": 2223.0,
      "clickRate": 0.0902
    },
    {
      "date": "2026-03-26",
      "emailAttributedRevenueCzk": 172876.9,
      "smsAttributedRevenueCzk": 0.0,
      "totalAttributedRevenueCzk": 172876.9,
      "emailAttributedOrders": 103.0,
      "smsAttributedOrders": 0.0,
      "totalAttributedOrders": 103.0,
      "emailRecipients": 29292.0,
      "smsRecipients": 0.0,
      "totalRecipients": 29292.0,
      "emailClicks": 1898.0,
      "smsClicks": 0.0,
      "totalClicks": 1898.0,
      "clickRate": 0.0648
    },
    {
      "date": "2026-03-27",
      "emailAttributedRevenueCzk": 120475.55,
      "smsAttributedRevenueCzk": 0.0,
      "totalAttributedRevenueCzk": 120475.55,
      "emailAttributedOrders": 73.0,
      "smsAttributedOrders": 0.0,
      "totalAttributedOrders": 73.0,
      "emailRecipients": 46919.0,
      "smsRecipients": 0.0,
      "totalRecipients": 46919.0,
      "emailClicks": 1385.0,
      "smsClicks": 0.0,
      "totalClicks": 1385.0,
      "clickRate": 0.0295
    },
    {
      "date": "2026-03-28",
      "emailAttributedRevenueCzk": 64567.75,
      "smsAttributedRevenueCzk": 0.0,
      "totalAttributedRevenueCzk": 64567.75,
      "emailAttributedOrders": 42.0,
      "smsAttributedOrders": 0.0,
      "totalAttributedOrders": 42.0,
      "emailRecipients": 24386.0,
      "smsRecipients": 0.0,
      "totalRecipients": 24386.0,
      "emailClicks": 830.0,
      "smsClicks": 0.0,
      "totalClicks": 830.0,
      "clickRate": 0.034
    },
    {
      "date": "2026-03-29",
      "emailAttributedRevenueCzk": 104622.05,
      "smsAttributedRevenueCzk": 0.0,
      "totalAttributedRevenueCzk": 104622.05,
      "emailAttributedOrders": 67.0,
      "smsAttributedOrders": 0.0,
      "totalAttributedOrders": 67.0,
      "emailRecipients": 44493.0,
      "smsRecipients": 0.0,
      "totalRecipients": 44493.0,
      "emailClicks": 1046.0,
      "smsClicks": 0.0,
      "totalClicks": 1046.0,
      "clickRate": 0.0235
    },
    {
      "date": "2026-03-30",
      "emailAttributedRevenueCzk": 201510.35,
      "smsAttributedRevenueCzk": 0.0,
      "totalAttributedRevenueCzk": 201510.35,
      "emailAttributedOrders": 130.0,
      "smsAttributedOrders": 0.0,
      "totalAttributedOrders": 130.0,
      "emailRecipients": 49873.0,
      "smsRecipients": 0.0,
      "totalRecipients": 49873.0,
      "emailClicks": 2224.0,
      "smsClicks": 0.0,
      "totalClicks": 2224.0,
      "clickRate": 0.0446
    },
    {
      "date": "2026-03-31",
      "emailAttributedRevenueCzk": 277692.5,
      "smsAttributedRevenueCzk": 0.0,
      "totalAttributedRevenueCzk": 277692.5,
      "emailAttributedOrders": 201.0,
      "smsAttributedOrders": 0.0,
      "totalAttributedOrders": 201.0,
      "emailRecipients": 72284.0,
      "smsRecipients": 0.0,
      "totalRecipients": 72284.0,
      "emailClicks": 2064.0,
      "smsClicks": 0.0,
      "totalClicks": 2064.0,
      "clickRate": 0.0286
    },
    {
      "date": "2026-04-01",
      "emailAttributedRevenueCzk": 0.0,
      "smsAttributedRevenueCzk": 0.0,
      "totalAttributedRevenueCzk": 0.0,
      "emailAttributedOrders": 0.0,
      "smsAttributedOrders": 0.0,
      "totalAttributedOrders": 0.0,
      "emailRecipients": 27.0,
      "smsRecipients": 0.0,
      "totalRecipients": 27.0,
      "emailClicks": 24.0,
      "smsClicks": 0.0,
      "totalClicks": 24.0,
      "clickRate": 0.8889
    }
  ],
  "flowsPreviousMonth": [
    {
      "flowId": "SXtWxm",
      "flowName": "Opuštěný košík - Standard",
      "status": "live",
      "triggerType": "Metric",
      "channel": "email",
      "attributedOrders": 225.0,
      "attributedRevenueCzk": 336752.95,
      "messageCount": 4,
      "messageNames": [
        "Abandoned Cart: Email 1",
        "Abandoned Cart: Email 2",
        "Abandoned Cart: Email 3",
        "Abandoned Cart: Email 4"
      ],
      "recipients": 12751.0,
      "opens": 2934.0,
      "clicks": 435.0,
      "openRate": 0.2301,
      "clickRate": 0.0341,
      "conversionRate": 0.0176
    },
    {
      "flowId": "XXhjck",
      "flowName": "Registrae Kurz hubnutí 2",
      "status": "live",
      "triggerType": "Metric",
      "channel": "email",
      "attributedOrders": 54.0,
      "attributedRevenueCzk": 98692.15,
      "messageCount": 1,
      "messageNames": [
        "Email #1"
      ],
      "recipients": 3291.0,
      "opens": 4396.0,
      "clicks": 3971.0,
      "openRate": 1.3358,
      "clickRate": 1.2066,
      "conversionRate": 0.0164
    },
    {
      "flowId": "SxBynF",
      "flowName": "Webinář - potvrzení registrace",
      "status": "live",
      "triggerType": "Metric",
      "channel": "email",
      "attributedOrders": 50.0,
      "attributedRevenueCzk": 89221.3,
      "messageCount": 1,
      "messageNames": [
        "Potvrzení registrace na webinář"
      ],
      "recipients": 2862.0,
      "opens": 3241.0,
      "clicks": 1119.0,
      "openRate": 1.1324,
      "clickRate": 0.391,
      "conversionRate": 0.0175
    },
    {
      "flowId": "VTgVba",
      "flowName": "Happy Birthday - Standard",
      "status": "live",
      "triggerType": "Date Based",
      "channel": "email",
      "attributedOrders": 40.0,
      "attributedRevenueCzk": 67465.3,
      "messageCount": 1,
      "messageNames": [
        "Dárek k narozeninám"
      ],
      "recipients": 1167.0,
      "opens": 1111.0,
      "clicks": 218.0,
      "openRate": 0.952,
      "clickRate": 0.1868,
      "conversionRate": 0.0343
    },
    {
      "flowId": "R5fKfn",
      "flowName": "Přihláška - potvrzení , kurs tělo jako kompas",
      "status": "live",
      "triggerType": "Metric",
      "channel": "email",
      "attributedOrders": 19.0,
      "attributedRevenueCzk": 38045.6,
      "messageCount": 1,
      "messageNames": [
        "potvrzení přihlášy"
      ],
      "recipients": 1073.0,
      "opens": 1032.0,
      "clicks": 671.0,
      "openRate": 0.9618,
      "clickRate": 0.6253,
      "conversionRate": 0.0177
    },
    {
      "flowId": "XNAruS",
      "flowName": "hubnutí - potvrzení registrace",
      "status": "live",
      "triggerType": "Metric",
      "channel": "email",
      "attributedOrders": 24.0,
      "attributedRevenueCzk": 31149.45,
      "messageCount": 1,
      "messageNames": [
        "Email #1"
      ],
      "recipients": 1391.0,
      "opens": 2198.0,
      "clicks": 1154.0,
      "openRate": 1.5802,
      "clickRate": 0.8296,
      "conversionRate": 0.0173
    },
    {
      "flowId": "VqgfET",
      "flowName": "Bonusové body - připsání",
      "status": "live",
      "triggerType": "Metric",
      "channel": "email",
      "attributedOrders": 17.0,
      "attributedRevenueCzk": 28428.05,
      "messageCount": 1,
      "messageNames": [
        "Email #1"
      ],
      "recipients": 1363.0,
      "opens": 677.0,
      "clicks": 36.0,
      "openRate": 0.4967,
      "clickRate": 0.0264,
      "conversionRate": 0.0125
    },
    {
      "flowId": "SLW4ei",
      "flowName": "tianDe - upozornění na dárky",
      "status": "live",
      "triggerType": "Metric",
      "channel": "email",
      "attributedOrders": 14.0,
      "attributedRevenueCzk": 21940.1,
      "messageCount": 1,
      "messageNames": [
        "Info o připravených dárcích"
      ],
      "recipients": 218.0,
      "opens": 132.0,
      "clicks": 13.0,
      "openRate": 0.6055,
      "clickRate": 0.0596,
      "conversionRate": 0.0642
    },
    {
      "flowId": "TFpngU",
      "flowName": "Kvíz Detox",
      "status": "live",
      "triggerType": "Metric",
      "channel": "email",
      "attributedOrders": 3.0,
      "attributedRevenueCzk": 9685.0,
      "messageCount": 4,
      "messageNames": [
        "Email #1 - prevence",
        "Email #1 - střední zátěž",
        "vysoká zátěž",
        "Email #4"
      ],
      "recipients": 132.0,
      "opens": 101.0,
      "clicks": 54.0,
      "openRate": 0.7652,
      "clickRate": 0.4091,
      "conversionRate": 0.0227
    },
    {
      "flowId": "RsXZp7",
      "flowName": "Affiliate - Password reset",
      "status": "live",
      "triggerType": "Metric",
      "channel": "email",
      "attributedOrders": 3.0,
      "attributedRevenueCzk": 5113.0,
      "messageCount": 1,
      "messageNames": [
        "Obnova hesla"
      ],
      "recipients": 10.0,
      "opens": 5.0,
      "clicks": 7.0,
      "openRate": 0.5,
      "clickRate": 0.7,
      "conversionRate": 0.3
    },
    {
      "flowId": "WMS3b5",
      "flowName": "welcome - brožury - bez bolesti",
      "status": "live",
      "triggerType": "Added to List",
      "channel": "email",
      "attributedOrders": 1.0,
      "attributedRevenueCzk": 3976.0,
      "messageCount": 9,
      "messageNames": [
        "Email #1",
        "Email #2",
        "Email #3",
        "Email #4",
        "Email #5"
      ],
      "recipients": 1186.0,
      "opens": 275.0,
      "clicks": 61.0,
      "openRate": 0.2319,
      "clickRate": 0.0514,
      "conversionRate": 0.0008
    },
    {
      "flowId": "R7vYcG",
      "flowName": "Registrace tianDe ID",
      "status": "live",
      "triggerType": "Metric",
      "channel": "email",
      "attributedOrders": 1.0,
      "attributedRevenueCzk": 78.15,
      "messageCount": 1,
      "messageNames": [
        "Email #1"
      ],
      "recipients": 7.0,
      "opens": 5.0,
      "clicks": 1.0,
      "openRate": 0.7143,
      "clickRate": 0.1429,
      "conversionRate": 0.1429
    },
    {
      "flowId": "XkGhDa",
      "flowName": "Affiliate - pending partner created",
      "status": "live",
      "triggerType": "Metric",
      "channel": "email",
      "attributedOrders": 1.0,
      "attributedRevenueCzk": 69.8,
      "messageCount": 1,
      "messageNames": [
        "Email #1"
      ],
      "recipients": 8.0,
      "opens": 8.0,
      "clicks": 2.0,
      "openRate": 1.0,
      "clickRate": 0.25,
      "conversionRate": 0.125
    }
  ],
  "topFlowsPreviousMonth": [
    {
      "flowId": "SXtWxm",
      "flowName": "Opuštěný košík - Standard",
      "status": "live",
      "triggerType": "Metric",
      "channel": "email",
      "attributedOrders": 225.0,
      "attributedRevenueCzk": 336752.95,
      "messageCount": 4,
      "messageNames": [
        "Abandoned Cart: Email 1",
        "Abandoned Cart: Email 2",
        "Abandoned Cart: Email 3",
        "Abandoned Cart: Email 4"
      ],
      "recipients": 12751.0,
      "opens": 2934.0,
      "clicks": 435.0,
      "openRate": 0.2301,
      "clickRate": 0.0341,
      "conversionRate": 0.0176
    },
    {
      "flowId": "XXhjck",
      "flowName": "Registrae Kurz hubnutí 2",
      "status": "live",
      "triggerType": "Metric",
      "channel": "email",
      "attributedOrders": 54.0,
      "attributedRevenueCzk": 98692.15,
      "messageCount": 1,
      "messageNames": [
        "Email #1"
      ],
      "recipients": 3291.0,
      "opens": 4396.0,
      "clicks": 3971.0,
      "openRate": 1.3358,
      "clickRate": 1.2066,
      "conversionRate": 0.0164
    },
    {
      "flowId": "SxBynF",
      "flowName": "Webinář - potvrzení registrace",
      "status": "live",
      "triggerType": "Metric",
      "channel": "email",
      "attributedOrders": 50.0,
      "attributedRevenueCzk": 89221.3,
      "messageCount": 1,
      "messageNames": [
        "Potvrzení registrace na webinář"
      ],
      "recipients": 2862.0,
      "opens": 3241.0,
      "clicks": 1119.0,
      "openRate": 1.1324,
      "clickRate": 0.391,
      "conversionRate": 0.0175
    },
    {
      "flowId": "VTgVba",
      "flowName": "Happy Birthday - Standard",
      "status": "live",
      "triggerType": "Date Based",
      "channel": "email",
      "attributedOrders": 40.0,
      "attributedRevenueCzk": 67465.3,
      "messageCount": 1,
      "messageNames": [
        "Dárek k narozeninám"
      ],
      "recipients": 1167.0,
      "opens": 1111.0,
      "clicks": 218.0,
      "openRate": 0.952,
      "clickRate": 0.1868,
      "conversionRate": 0.0343
    },
    {
      "flowId": "R5fKfn",
      "flowName": "Přihláška - potvrzení , kurs tělo jako kompas",
      "status": "live",
      "triggerType": "Metric",
      "channel": "email",
      "attributedOrders": 19.0,
      "attributedRevenueCzk": 38045.6,
      "messageCount": 1,
      "messageNames": [
        "potvrzení přihlášy"
      ],
      "recipients": 1073.0,
      "opens": 1032.0,
      "clicks": 671.0,
      "openRate": 0.9618,
      "clickRate": 0.6253,
      "conversionRate": 0.0177
    },
    {
      "flowId": "XNAruS",
      "flowName": "hubnutí - potvrzení registrace",
      "status": "live",
      "triggerType": "Metric",
      "channel": "email",
      "attributedOrders": 24.0,
      "attributedRevenueCzk": 31149.45,
      "messageCount": 1,
      "messageNames": [
        "Email #1"
      ],
      "recipients": 1391.0,
      "opens": 2198.0,
      "clicks": 1154.0,
      "openRate": 1.5802,
      "clickRate": 0.8296,
      "conversionRate": 0.0173
    },
    {
      "flowId": "VqgfET",
      "flowName": "Bonusové body - připsání",
      "status": "live",
      "triggerType": "Metric",
      "channel": "email",
      "attributedOrders": 17.0,
      "attributedRevenueCzk": 28428.05,
      "messageCount": 1,
      "messageNames": [
        "Email #1"
      ],
      "recipients": 1363.0,
      "opens": 677.0,
      "clicks": 36.0,
      "openRate": 0.4967,
      "clickRate": 0.0264,
      "conversionRate": 0.0125
    },
    {
      "flowId": "SLW4ei",
      "flowName": "tianDe - upozornění na dárky",
      "status": "live",
      "triggerType": "Metric",
      "channel": "email",
      "attributedOrders": 14.0,
      "attributedRevenueCzk": 21940.1,
      "messageCount": 1,
      "messageNames": [
        "Info o připravených dárcích"
      ],
      "recipients": 218.0,
      "opens": 132.0,
      "clicks": 13.0,
      "openRate": 0.6055,
      "clickRate": 0.0596,
      "conversionRate": 0.0642
    },
    {
      "flowId": "TFpngU",
      "flowName": "Kvíz Detox",
      "status": "live",
      "triggerType": "Metric",
      "channel": "email",
      "attributedOrders": 3.0,
      "attributedRevenueCzk": 9685.0,
      "messageCount": 4,
      "messageNames": [
        "Email #1 - prevence",
        "Email #1 - střední zátěž",
        "vysoká zátěž",
        "Email #4"
      ],
      "recipients": 132.0,
      "opens": 101.0,
      "clicks": 54.0,
      "openRate": 0.7652,
      "clickRate": 0.4091,
      "conversionRate": 0.0227
    },
    {
      "flowId": "RsXZp7",
      "flowName": "Affiliate - Password reset",
      "status": "live",
      "triggerType": "Metric",
      "channel": "email",
      "attributedOrders": 3.0,
      "attributedRevenueCzk": 5113.0,
      "messageCount": 1,
      "messageNames": [
        "Obnova hesla"
      ],
      "recipients": 10.0,
      "opens": 5.0,
      "clicks": 7.0,
      "openRate": 0.5,
      "clickRate": 0.7,
      "conversionRate": 0.3
    }
  ],
  "recentCampaignsPreviousMonth": []
}